{
   "book": [
     { "id": "p1", "zIndex": 4, "isCover": true, "backContent": { "title": "To My Bestie Saumya,", "text": "A special chapter in the beautiful book of your life...", "symbol": "💎" }, "frontContent": { "coverImg": "./assets/ss (1).jpg", "title": "The Golden Days of Saumya", "chapter": "Chapter 2026", "footer": "Keep Moving Forward" } },
     { "id": "p2", "zIndex": 3, "backContent": { "img": "./assets/ss (2).jpg", "text": "\"A heart of gold\" 💛" }, "frontContent": { "img": "./assets/ss (3).jpg", "text": "\"A gathering of memories\" 🎞️" } },
     { "id": "p3", "zIndex": 2, "backContent": { "img": "./assets/ss (4).jpg", "text": "\"Courage and tenderness\" 💪" }, "frontContent": { "img": "./assets/ss (5).jpg", "text": "\"Big dreams\" 🚀" } },
     { "id": "p4", "zIndex": 1, "backContent": { "title": "Always Stay Awesome", "text": "The world is incomplete without a friend like you!" }, "frontContent": { "img": "./assets/ss (6).jpg", "text": "\"That iconic vibe\" ✨" } }
   ],
   "memories": [
     { "img": "./assets/ss (7).jpg", "title": "Amazing Friend...", "desc": "I was thinking about our funny moments today and couldn't help but laugh. Your presence always lightens the mood." },
     { "img": "./assets/ss (8).jpg", "title": "Best Therapist ✨", "desc": "Whenever I talk to you and we start our random gossips, all my worries just disappear. ✨" },
     { "img": "./assets/ss (9).jpg", "title": "Growing Together", "desc": "Like our awesome bond, you just keep getting wiser and more fun with every passing day. 😍" },
     { "img": "./assets/ss (10).jpg", "title": "Endless Drama", "desc": "I am always ready for our endless gossips, random discussions, and daily drama! 🌟" },
     { "img": "./assets/ss (11).jpg", "title": "Crazy Times", "desc": "Every time I look at our crazy pictures together, I just can't stop smiling at our stupidity." },
     { "img": "./assets/ss (12).jpg", "title": "Your Positivity..", "desc": "Your positive energy and bright smile always bring good vibes." },
     { "img": "./assets/ss (13).jpg", "title": "Kind Soul..", "desc": "You have a genuinely kind heart and always support your friends." },
     { "img": "./assets/ss (14).jpg", "title": "Fun Moments..", "desc": "Every single moment spent with our group becomes a hilarious memory." },
     { "img": "./assets/ss (15).jpg", "title": "Endless Laughter..", "desc": "Having a best friend like you around brings endless joy and laughter." },
     { "img": "./assets/ss (16).jpg", "title": "Forever Besties..", "desc": "Always stay this crazy and keep shining bright." }
   ],
   "carousel": [
     { "title": "Hi 👋", "num": "01", "img": "./assets/ss (17).jpg" },
     { "title": "I want to tell you Something 😎", "num": "02", "img": "./assets/ss (18).jpg" },
     { "title": "Please Keep Dragging 😊", "num": "03", "img": "./assets/ss (19).jpg" },
     { "title": "You are an Amazing Friend 🤩", "num": "04", "img": "./assets/ss (20).jpg" },
     { "title": "Always so Supportive 💯", "num": "05", "img": "./assets/ss (21).jpg" },
     { "title": "And Super Fun! 🎉", "num": "06", "img": "./assets/ss (22).jpg" },
     { "title": "Honestly speaking... 😇", "num": "07", "img": "./assets/ss (23).jpg" },
     { "title": "Always by my side 🤝", "num": "08", "img": "./assets/ss (24).jpg" },
     { "title": "And my favorite headache! 😂", "num": "09", "img": "./assets/ss (25).jpg" },
     { "title": "Happy Birthday, Yaar! 🎂", "num": "10", "img": "./assets/ss (26).jpg" }
   ],
   "spinner": [
     { "img": "./assets/ss (27).jpg" },
     { "img": "./assets/ss (28).jpg" },
     { "img": "./assets/ss (29).jpg" },
     { "img": "./assets/ss (30).jpg" },
     { "img": "./assets/ss (31).jpg" },
     { "img": "./assets/ss (32).jpg" },
     { "img": "./assets/ss (33).jpg" },
     { "img": "./assets/ss (34).jpg" },
     { "img": "./assets/ss (35).jpg" },
     { "img": "./assets/ss (36).jpg" }
   ],
   "jhoomar": [
     { "img": "./assets/ss (37).jpg" },
     { "img": "./assets/ss (38).jpg" },
     { "img": "./assets/ss (39).jpg" },
     { "img": "./assets/ss (40).jpg" },
     { "img": "./assets/ss (41).jpg" },
     { "img": "./assets/ss (42).jpg" },
     { "img": "./assets/ss (43).jpg" },
     { "img": "./assets/ss (44).jpg" },
     { "img": "./assets/ss (45).jpg" },
     { "img": "./assets/ss (46).jpg" }
   ],
    "saumyaImages": [
      "./assets/ss (12).jpg",
      "./assets/ss (13).jpg",
      "./assets/ss (17).jpg",
      "./assets/ss (19).jpg"
    ],
    "musicList": [
      { "name": "Somu Special Song 1", "src": "./assets/music.mp3" },
      { "name": "Cute Background Music", "src": "./assets/music2.mp3" }
    ],
    "magicalGallery": [
     { "id": "vid_1", "type": "video", "src": "./assets/ss (1).mp4", "frontNote": "Our Funniest Moment 🎥", "backNote": "This hilarious moment will always be cherished! 😂", "isMain": true },
     { "id": "pic_1", "type": "image", "src": "./assets/ss (47).jpg", "frontNote": "Above the Clouds ☁️", "backNote": "Wishing you always reach for the sky and achieve your goals!" },
     { "id": "pic_2", "type": "image", "src": "./assets/ss (48).jpg", "frontNote": "Best Vibe 💯", "backNote": "Your positive energy is unmatched. Nazar na lage! 🧿" },
     { "id": "pic_3", "type": "image", "src": "./assets/ss (49).jpg", "frontNote": "That Sweet Smile 😊", "backNote": "Your cheerful nature brightens everyone's day around you." },
     { "id": "pic_4", "type": "image", "src": "./assets/ss (50).jpg", "frontNote": "Crazy Memories ✨", "backNote": "Some hilarious moments that we will never forget." },
     { "id": "pic_5", "type": "image", "src": "./assets/ss (51).jpg", "frontNote": "Stay Protected 🧿", "backNote": "Always be safe and keep progressing in life." },
     { "id": "pic_6", "type": "image", "src": "./assets/ss (52).jpg", "frontNote": "Great Friends 🤝", "backNote": "May our friendly banters and gossips never end." },
     { "id": "pic_7", "type": "image", "src": "./assets/ss (53).jpg", "frontNote": "Happiness 🌟", "backNote": "May you get all the success you deserve." },
     { "id": "pic_8", "type": "image", "src": "./assets/ss (54).jpg", "frontNote": "Golden Times 🕰️", "backNote": "School/College days are always the most precious." },
     { "id": "pic_9", "type": "image", "src": "./assets/ss (55).jpg", "frontNote": "Perfect Clicks 📸", "backNote": "A picture perfect moment with the gang!" },
     { "id": "pic_10", "type": "image", "src": "./assets/ss (56).jpg", "frontNote": "My Bestie ✌️", "backNote": "A true friend for life! Always got your back." }
   ],
   "carouselCards": [
     { "num": "01", "title": "Hi 👋", "img": "./assets/ss (57).jpg" },
     { "num": "02", "title": "I want to tell you Something 😎", "img": "./assets/ss (58).jpg" },
     { "num": "03", "title": "Please Keep Dragging 😊", "img": "./assets/ss (59).jpg" },
     { "num": "04", "title": "You are an Amazing Friend 🤩", "img": "./assets/ss (60).jpg" },
     { "num": "05", "title": "Always so Supportive 💯", "img": "./assets/ss (61).jpg" },
     { "num": "06", "title": "And Super Fun! 🎉", "img": "./assets/ss (62).jpg" },
     { "num": "07", "title": "Honestly speaking... 😇", "img": "./assets/ss (63).jpg" },
     { "num": "08", "title": "Always by my side 🤝", "img": "./assets/ss (64).jpg" },
     { "num": "09", "title": "And my favorite headache! 😂", "img": "./assets/ss (65).jpg" },
     { "num": "10", "title": "Happy Birthday, Yaar! 🎂", "img": "./assets/ss (66).jpg" },
     { "num": "11", "title": "Keep Smiling ✨", "img": "./assets/ss (67).jpg" },
     { "num": "12", "title": "Stay Awesome 🌟", "img": "./assets/ss (68).jpg" },
     { "num": "13", "title": "You're a True Gem 💎", "img": "./assets/ss (69).jpg" },
     { "num": "14", "title": "Crazy Memories 📸", "img": "./assets/ss (70).jpg" },
     { "num": "15", "title": "Have a Blast! 🎉", "img": "./assets/ss (71).jpg" }
   ],
   "animatedFrame": {
     "text": "HAPPY BIRTHDAY SAUMYA",
     "img": "./assets/ss (72).jpg"
    }
}
